{
  "a_comp_cor_00": {
    "CumulativeVarianceExplained": 0.0338148605,
    "Mask": "combined",
    "Method": "aCompCor",
    "Retained": true,
    "SingularValue": 109.5809979692,
    "VarianceExplained": 0.0338148605
  },
  "a_comp_cor_01": {
    "CumulativeVarianceExplained": 0.0628469849,
    "Mask": "combined",
    "Method": "aCompCor",
    "Retained": true,
    "SingularValue": 101.5361890384,
    "VarianceExplained": 0.0290321244
  },
  "a_comp_cor_02": {
    "CumulativeVarianceExplained": 0.0872340231,
    "Mask": "combined",
    "Method": "aCompCor",
    "Retained": true,
    "SingularValue": 93.0595568952,
    "VarianceExplained": 0.0243870382
  },
  "a_comp_cor_03": {
    "CumulativeVarianceExplained": 0.1061664195,
    "Mask": "combined",
    "Method": "aCompCor",
    "Retained": true,
    "SingularValue": 81.9944100715,
    "VarianceExplained": 0.0189323964
  },
  "a_comp_cor_04": {
    "CumulativeVarianceExplained": 0.116938246,
    "Mask": "combined",
    "Method": "aCompCor",
    "Retained": true,
    "SingularValue": 61.8480664207,
    "VarianceExplained": 0.0107718265
  },
  "a_comp_cor_05": {
    "CumulativeVarianceExplained": 0.1274905607,
    "Mask": "combined",
    "Method": "aCompCor",
    "Retained": true,
    "SingularValue": 61.2146426684,
    "VarianceExplained": 0.0105523147
  },
  "a_comp_cor_06": {
    "CumulativeVarianceExplained": 0.137170806,
    "Mask": "combined",
    "Method": "aCompCor",
    "Retained": true,
    "SingularValue": 58.6306397878,
    "VarianceExplained": 0.0096802453
  },
  "a_comp_cor_07": {
    "CumulativeVarianceExplained": 0.146494815,
    "Mask": "combined",
    "Method": "aCompCor",
    "Retained": true,
    "SingularValue": 57.5417137309,
    "VarianceExplained": 0.009324009
  },
  "a_comp_cor_08": {
    "CumulativeVarianceExplained": 0.1553112847,
    "Mask": "combined",
    "Method": "aCompCor",
    "Retained": true,
    "SingularValue": 55.9537002548,
    "VarianceExplained": 0.0088164697
  },
  "a_comp_cor_09": {
    "CumulativeVarianceExplained": 0.1638918565,
    "Mask": "combined",
    "Method": "aCompCor",
    "Retained": true,
    "SingularValue": 55.2000620015,
    "VarianceExplained": 0.0085805718
  },
  "a_comp_cor_10": {
    "CumulativeVarianceExplained": 0.1723864998,
    "Mask": "combined",
    "Method": "aCompCor",
    "Retained": true,
    "SingularValue": 54.922971442,
    "VarianceExplained": 0.0084946433
  },
  "a_comp_cor_11": {
    "CumulativeVarianceExplained": 0.1807446378,
    "Mask": "combined",
    "Method": "aCompCor",
    "Retained": true,
    "SingularValue": 54.479889457,
    "VarianceExplained": 0.0083581379
  },
  "a_comp_cor_12": {
    "CumulativeVarianceExplained": 0.189039578,
    "Mask": "combined",
    "Method": "aCompCor",
    "Retained": true,
    "SingularValue": 54.2735314858,
    "VarianceExplained": 0.0082949402
  },
  "a_comp_cor_13": {
    "CumulativeVarianceExplained": 0.1972607796,
    "Mask": "combined",
    "Method": "aCompCor",
    "Retained": true,
    "SingularValue": 54.0317582365,
    "VarianceExplained": 0.0082212016
  },
  "a_comp_cor_14": {
    "CumulativeVarianceExplained": 0.2053435788,
    "Mask": "combined",
    "Method": "aCompCor",
    "Retained": true,
    "SingularValue": 53.5750206699,
    "VarianceExplained": 0.0080827992
  },
  "a_comp_cor_15": {
    "CumulativeVarianceExplained": 0.2133081054,
    "Mask": "combined",
    "Method": "aCompCor",
    "Retained": true,
    "SingularValue": 53.1816043059,
    "VarianceExplained": 0.0079645266
  },
  "a_comp_cor_16": {
    "CumulativeVarianceExplained": 0.2212288549,
    "Mask": "combined",
    "Method": "aCompCor",
    "Retained": true,
    "SingularValue": 53.0352463608,
    "VarianceExplained": 0.0079207495
  },
  "a_comp_cor_17": {
    "CumulativeVarianceExplained": 0.2290940916,
    "Mask": "combined",
    "Method": "aCompCor",
    "Retained": true,
    "SingularValue": 52.8490700203,
    "VarianceExplained": 0.0078652367
  },
  "a_comp_cor_18": {
    "CumulativeVarianceExplained": 0.2368479462,
    "Mask": "combined",
    "Method": "aCompCor",
    "Retained": true,
    "SingularValue": 52.4735297506,
    "VarianceExplained": 0.0077538546
  },
  "a_comp_cor_19": {
    "CumulativeVarianceExplained": 0.2444440462,
    "Mask": "combined",
    "Method": "aCompCor",
    "Retained": true,
    "SingularValue": 51.9369912303,
    "VarianceExplained": 0.0075961
  },
  "a_comp_cor_20": {
    "CumulativeVarianceExplained": 0.2519763952,
    "Mask": "combined",
    "Method": "aCompCor",
    "Retained": true,
    "SingularValue": 51.7185890795,
    "VarianceExplained": 0.007532349
  },
  "a_comp_cor_21": {
    "CumulativeVarianceExplained": 0.2594497793,
    "Mask": "combined",
    "Method": "aCompCor",
    "Retained": true,
    "SingularValue": 51.515758913,
    "VarianceExplained": 0.0074733841
  },
  "a_comp_cor_22": {
    "CumulativeVarianceExplained": 0.2667670175,
    "Mask": "combined",
    "Method": "aCompCor",
    "Retained": true,
    "SingularValue": 50.9747433373,
    "VarianceExplained": 0.0073172382
  },
  "a_comp_cor_23": {
    "CumulativeVarianceExplained": 0.2740725133,
    "Mask": "combined",
    "Method": "aCompCor",
    "Retained": true,
    "SingularValue": 50.9338260194,
    "VarianceExplained": 0.0073054959
  },
  "a_comp_cor_24": {
    "CumulativeVarianceExplained": 0.2813127666,
    "Mask": "combined",
    "Method": "aCompCor",
    "Retained": true,
    "SingularValue": 50.7058807975,
    "VarianceExplained": 0.0072402533
  },
  "a_comp_cor_25": {
    "CumulativeVarianceExplained": 0.2885241578,
    "Mask": "combined",
    "Method": "aCompCor",
    "Retained": true,
    "SingularValue": 50.6047143351,
    "VarianceExplained": 0.0072113912
  },
  "a_comp_cor_26": {
    "CumulativeVarianceExplained": 0.2956900271,
    "Mask": "combined",
    "Method": "aCompCor",
    "Retained": true,
    "SingularValue": 50.4447406775,
    "VarianceExplained": 0.0071658693
  },
  "a_comp_cor_27": {
    "CumulativeVarianceExplained": 0.3027961398,
    "Mask": "combined",
    "Method": "aCompCor",
    "Retained": true,
    "SingularValue": 50.233969191,
    "VarianceExplained": 0.0071061126
  },
  "a_comp_cor_28": {
    "CumulativeVarianceExplained": 0.3098572941,
    "Mask": "combined",
    "Method": "aCompCor",
    "Retained": true,
    "SingularValue": 50.07480909,
    "VarianceExplained": 0.0070611543
  },
  "a_comp_cor_29": {
    "CumulativeVarianceExplained": 0.3168751327,
    "Mask": "combined",
    "Method": "aCompCor",
    "Retained": true,
    "SingularValue": 49.9209842661,
    "VarianceExplained": 0.0070178386
  },
  "a_comp_cor_30": {
    "CumulativeVarianceExplained": 0.3238500787,
    "Mask": "combined",
    "Method": "aCompCor",
    "Retained": true,
    "SingularValue": 49.7681933582,
    "VarianceExplained": 0.006974946
  },
  "a_comp_cor_31": {
    "CumulativeVarianceExplained": 0.3307755654,
    "Mask": "combined",
    "Method": "aCompCor",
    "Retained": true,
    "SingularValue": 49.5914266261,
    "VarianceExplained": 0.0069254867
  },
  "a_comp_cor_32": {
    "CumulativeVarianceExplained": 0.3376337674,
    "Mask": "combined",
    "Method": "aCompCor",
    "Retained": true,
    "SingularValue": 49.3499353607,
    "VarianceExplained": 0.006858202
  },
  "a_comp_cor_33": {
    "CumulativeVarianceExplained": 0.344390931,
    "Mask": "combined",
    "Method": "aCompCor",
    "Retained": true,
    "SingularValue": 48.9850625647,
    "VarianceExplained": 0.0067571636
  },
  "a_comp_cor_34": {
    "CumulativeVarianceExplained": 0.3510906933,
    "Mask": "combined",
    "Method": "aCompCor",
    "Retained": true,
    "SingularValue": 48.7765577783,
    "VarianceExplained": 0.0066997623
  },
  "a_comp_cor_35": {
    "CumulativeVarianceExplained": 0.3577855138,
    "Mask": "combined",
    "Method": "aCompCor",
    "Retained": true,
    "SingularValue": 48.7585654164,
    "VarianceExplained": 0.0066948205
  },
  "a_comp_cor_36": {
    "CumulativeVarianceExplained": 0.3644051322,
    "Mask": "combined",
    "Method": "aCompCor",
    "Retained": true,
    "SingularValue": 48.483942641,
    "VarianceExplained": 0.0066196184
  },
  "a_comp_cor_37": {
    "CumulativeVarianceExplained": 0.3709885405,
    "Mask": "combined",
    "Method": "aCompCor",
    "Retained": true,
    "SingularValue": 48.3511541461,
    "VarianceExplained": 0.0065834083
  },
  "a_comp_cor_38": {
    "CumulativeVarianceExplained": 0.3775599717,
    "Mask": "combined",
    "Method": "aCompCor",
    "Retained": true,
    "SingularValue": 48.3071522237,
    "VarianceExplained": 0.0065714313
  },
  "a_comp_cor_39": {
    "CumulativeVarianceExplained": 0.3841041044,
    "Mask": "combined",
    "Method": "aCompCor",
    "Retained": true,
    "SingularValue": 48.2067108108,
    "VarianceExplained": 0.0065441327
  },
  "a_comp_cor_40": {
    "CumulativeVarianceExplained": 0.3905865268,
    "Mask": "combined",
    "Method": "aCompCor",
    "Retained": true,
    "SingularValue": 47.9788807005,
    "VarianceExplained": 0.0064824223
  },
  "a_comp_cor_41": {
    "CumulativeVarianceExplained": 0.3969819684,
    "Mask": "combined",
    "Method": "aCompCor",
    "Retained": true,
    "SingularValue": 47.6559050728,
    "VarianceExplained": 0.0063954417
  },
  "a_comp_cor_42": {
    "CumulativeVarianceExplained": 0.4033415539,
    "Mask": "combined",
    "Method": "aCompCor",
    "Retained": true,
    "SingularValue": 47.5221252177,
    "VarianceExplained": 0.0063595854
  },
  "a_comp_cor_43": {
    "CumulativeVarianceExplained": 0.4096866091,
    "Mask": "combined",
    "Method": "aCompCor",
    "Retained": true,
    "SingularValue": 47.4678056619,
    "VarianceExplained": 0.0063450553
  },
  "a_comp_cor_44": {
    "CumulativeVarianceExplained": 0.4160173325,
    "Mask": "combined",
    "Method": "aCompCor",
    "Retained": true,
    "SingularValue": 47.4141665297,
    "VarianceExplained": 0.0063307234
  },
  "a_comp_cor_45": {
    "CumulativeVarianceExplained": 0.4222710546,
    "Mask": "combined",
    "Method": "aCompCor",
    "Retained": true,
    "SingularValue": 47.124932134,
    "VarianceExplained": 0.006253722
  },
  "a_comp_cor_46": {
    "CumulativeVarianceExplained": 0.428495331,
    "Mask": "combined",
    "Method": "aCompCor",
    "Retained": true,
    "SingularValue": 47.013857412,
    "VarianceExplained": 0.0062242764
  },
  "a_comp_cor_47": {
    "CumulativeVarianceExplained": 0.4346500011,
    "Mask": "combined",
    "Method": "aCompCor",
    "Retained": true,
    "SingularValue": 46.7502396384,
    "VarianceExplained": 0.0061546701
  },
  "a_comp_cor_48": {
    "CumulativeVarianceExplained": 0.4407963121,
    "Mask": "combined",
    "Method": "aCompCor",
    "Retained": true,
    "SingularValue": 46.7184812691,
    "VarianceExplained": 0.006146311
  },
  "a_comp_cor_49": {
    "CumulativeVarianceExplained": 0.4468974846,
    "Mask": "combined",
    "Method": "aCompCor",
    "Retained": true,
    "SingularValue": 46.5466151544,
    "VarianceExplained": 0.0061011725
  },
  "a_comp_cor_50": {
    "CumulativeVarianceExplained": 0.4529666427,
    "Mask": "combined",
    "Method": "aCompCor",
    "Retained": true,
    "SingularValue": 46.4243335606,
    "VarianceExplained": 0.0060691581
  },
  "a_comp_cor_51": {
    "CumulativeVarianceExplained": 0.4589933866,
    "Mask": "combined",
    "Method": "aCompCor",
    "Retained": true,
    "SingularValue": 46.2618310896,
    "VarianceExplained": 0.0060267439
  },
  "a_comp_cor_52": {
    "CumulativeVarianceExplained": 0.4650123426,
    "Mask": "combined",
    "Method": "aCompCor",
    "Retained": true,
    "SingularValue": 46.2319313376,
    "VarianceExplained": 0.006018956
  },
  "a_comp_cor_53": {
    "CumulativeVarianceExplained": 0.4710027702,
    "Mask": "combined",
    "Method": "aCompCor",
    "Retained": true,
    "SingularValue": 46.1222370102,
    "VarianceExplained": 0.0059904276
  },
  "a_comp_cor_54": {
    "CumulativeVarianceExplained": 0.4769393555,
    "Mask": "combined",
    "Method": "aCompCor",
    "Retained": true,
    "SingularValue": 45.9144943177,
    "VarianceExplained": 0.0059365853
  },
  "a_comp_cor_55": {
    "CumulativeVarianceExplained": 0.4828307201,
    "Mask": "combined",
    "Method": "aCompCor",
    "Retained": true,
    "SingularValue": 45.7392884094,
    "VarianceExplained": 0.0058913647
  },
  "a_comp_cor_56": {
    "CumulativeVarianceExplained": 0.488714518,
    "Mask": "combined",
    "Method": "aCompCor",
    "Retained": true,
    "SingularValue": 45.7099053592,
    "VarianceExplained": 0.0058837978
  },
  "a_comp_cor_57": {
    "CumulativeVarianceExplained": 0.4945596942,
    "Mask": "combined",
    "Method": "aCompCor",
    "Retained": true,
    "SingularValue": 45.5596369609,
    "VarianceExplained": 0.0058451762
  },
  "a_comp_cor_58": {
    "CumulativeVarianceExplained": 0.5003619832,
    "Mask": "combined",
    "Method": "aCompCor",
    "Retained": true,
    "SingularValue": 45.392189224,
    "VarianceExplained": 0.005802289
  },
  "c_comp_cor_00": {
    "CumulativeVarianceExplained": 0.1248914166,
    "Mask": "CSF",
    "Method": "aCompCor",
    "Retained": true,
    "SingularValue": 83.8086706126,
    "VarianceExplained": 0.1248914166
  },
  "c_comp_cor_01": {
    "CumulativeVarianceExplained": 0.217046938,
    "Mask": "CSF",
    "Method": "aCompCor",
    "Retained": true,
    "SingularValue": 71.9918504037,
    "VarianceExplained": 0.0921555214
  },
  "c_comp_cor_02": {
    "CumulativeVarianceExplained": 0.2713575112,
    "Mask": "CSF",
    "Method": "aCompCor",
    "Retained": true,
    "SingularValue": 55.2668674159,
    "VarianceExplained": 0.0543105732
  },
  "c_comp_cor_03": {
    "CumulativeVarianceExplained": 0.3130388706,
    "Mask": "CSF",
    "Method": "aCompCor",
    "Retained": true,
    "SingularValue": 48.4165225526,
    "VarianceExplained": 0.0416813595
  },
  "c_comp_cor_04": {
    "CumulativeVarianceExplained": 0.3413223218,
    "Mask": "CSF",
    "Method": "aCompCor",
    "Retained": true,
    "SingularValue": 39.8830953161,
    "VarianceExplained": 0.0282834511
  },
  "c_comp_cor_05": {
    "CumulativeVarianceExplained": 0.366018463,
    "Mask": "CSF",
    "Method": "aCompCor",
    "Retained": true,
    "SingularValue": 37.2680960774,
    "VarianceExplained": 0.0246961413
  },
  "c_comp_cor_06": {
    "CumulativeVarianceExplained": 0.3866087024,
    "Mask": "CSF",
    "Method": "aCompCor",
    "Retained": true,
    "SingularValue": 34.0293264654,
    "VarianceExplained": 0.0205902393
  },
  "c_comp_cor_07": {
    "CumulativeVarianceExplained": 0.4038527521,
    "Mask": "CSF",
    "Method": "aCompCor",
    "Retained": true,
    "SingularValue": 31.1416980424,
    "VarianceExplained": 0.0172440497
  },
  "c_comp_cor_08": {
    "CumulativeVarianceExplained": 0.4197994132,
    "Mask": "CSF",
    "Method": "aCompCor",
    "Retained": true,
    "SingularValue": 29.9472906665,
    "VarianceExplained": 0.0159466611
  },
  "c_comp_cor_09": {
    "CumulativeVarianceExplained": 0.4346274263,
    "Mask": "CSF",
    "Method": "aCompCor",
    "Retained": true,
    "SingularValue": 28.8778021859,
    "VarianceExplained": 0.0148280131
  },
  "c_comp_cor_10": {
    "CumulativeVarianceExplained": 0.4490072129,
    "Mask": "CSF",
    "Method": "aCompCor",
    "Retained": true,
    "SingularValue": 28.4379886243,
    "VarianceExplained": 0.0143797866
  },
  "c_comp_cor_11": {
    "CumulativeVarianceExplained": 0.4623315392,
    "Mask": "CSF",
    "Method": "aCompCor",
    "Retained": true,
    "SingularValue": 27.3744427046,
    "VarianceExplained": 0.0133243263
  },
  "c_comp_cor_12": {
    "CumulativeVarianceExplained": 0.4753632054,
    "Mask": "CSF",
    "Method": "aCompCor",
    "Retained": true,
    "SingularValue": 27.0721425878,
    "VarianceExplained": 0.0130316662
  },
  "c_comp_cor_13": {
    "CumulativeVarianceExplained": 0.4872919898,
    "Mask": "CSF",
    "Method": "aCompCor",
    "Retained": true,
    "SingularValue": 25.9012516178,
    "VarianceExplained": 0.0119287844
  },
  "c_comp_cor_14": {
    "CumulativeVarianceExplained": 0.4986233099,
    "Mask": "CSF",
    "Method": "aCompCor",
    "Retained": true,
    "SingularValue": 25.244275457,
    "VarianceExplained": 0.0113313201
  },
  "c_comp_cor_15": {
    "CumulativeVarianceExplained": 0.5098626596,
    "Mask": "CSF",
    "Method": "aCompCor",
    "Retained": true,
    "SingularValue": 25.141619407,
    "VarianceExplained": 0.0112393497
  },
  "dropped_0": {
    "CumulativeVarianceExplained": 0.3858188723,
    "Mask": "Edge",
    "Method": "EdgeRegressor",
    "Retained": false,
    "SingularValue": 118.3331843618,
    "VarianceExplained": 0.006713915
  },
  "dropped_1": {
    "CumulativeVarianceExplained": 0.3924639253,
    "Mask": "Edge",
    "Method": "EdgeRegressor",
    "Retained": false,
    "SingularValue": 117.7247719145,
    "VarianceExplained": 0.006645053
  },
  "dropped_10": {
    "CumulativeVarianceExplained": 0.4457143274,
    "Mask": "Edge",
    "Method": "EdgeRegressor",
    "Retained": false,
    "SingularValue": 107.1479867195,
    "VarianceExplained": 0.0055046634
  },
  "dropped_100": {
    "CumulativeVarianceExplained": 0.8159620715,
    "Mask": "Edge",
    "Method": "EdgeRegressor",
    "Retained": false,
    "SingularValue": 84.5918355406,
    "VarianceExplained": 0.0034309914
  },
  "dropped_101": {
    "CumulativeVarianceExplained": 0.8193765666,
    "Mask": "Edge",
    "Method": "EdgeRegressor",
    "Retained": false,
    "SingularValue": 84.3882308239,
    "VarianceExplained": 0.0034144951
  },
  "dropped_102": {
    "CumulativeVarianceExplained": 0.822776183,
    "Mask": "Edge",
    "Method": "EdgeRegressor",
    "Retained": false,
    "SingularValue": 84.2041677347,
    "VarianceExplained": 0.0033996164
  },
  "dropped_103": {
    "CumulativeVarianceExplained": 0.826170924,
    "Mask": "Edge",
    "Method": "EdgeRegressor",
    "Retained": false,
    "SingularValue": 84.1437682983,
    "VarianceExplained": 0.003394741
  },
  "dropped_104": {
    "CumulativeVarianceExplained": 0.8295534202,
    "Mask": "Edge",
    "Method": "EdgeRegressor",
    "Retained": false,
    "SingularValue": 83.9918773025,
    "VarianceExplained": 0.0033824962
  },
  "dropped_105": {
    "CumulativeVarianceExplained": 0.832920787,
    "Mask": "Edge",
    "Method": "EdgeRegressor",
    "Retained": false,
    "SingularValue": 83.8038256062,
    "VarianceExplained": 0.0033673668
  },
  "dropped_106": {
    "CumulativeVarianceExplained": 0.836283605,
    "Mask": "Edge",
    "Method": "EdgeRegressor",
    "Retained": false,
    "SingularValue": 83.7472041269,
    "VarianceExplained": 0.003362818
  },
  "dropped_107": {
    "CumulativeVarianceExplained": 0.8396324657,
    "Mask": "Edge",
    "Method": "EdgeRegressor",
    "Retained": false,
    "SingularValue": 83.5732268598,
    "VarianceExplained": 0.0033488607
  },
  "dropped_108": {
    "CumulativeVarianceExplained": 0.8429640721,
    "Mask": "Edge",
    "Method": "EdgeRegressor",
    "Retained": false,
    "SingularValue": 83.3576535173,
    "VarianceExplained": 0.0033316065
  },
  "dropped_109": {
    "CumulativeVarianceExplained": 0.8462853276,
    "Mask": "Edge",
    "Method": "EdgeRegressor",
    "Retained": false,
    "SingularValue": 83.2280599284,
    "VarianceExplained": 0.0033212554
  },
  "dropped_11": {
    "CumulativeVarianceExplained": 0.4511572652,
    "Mask": "Edge",
    "Method": "EdgeRegressor",
    "Retained": false,
    "SingularValue": 106.5455512006,
    "VarianceExplained": 0.0054429379
  },
  "dropped_110": {
    "CumulativeVarianceExplained": 0.8495916982,
    "Mask": "Edge",
    "Method": "EdgeRegressor",
    "Retained": false,
    "SingularValue": 83.0413502343,
    "VarianceExplained": 0.0033063707
  },
  "dropped_111": {
    "CumulativeVarianceExplained": 0.8528943807,
    "Mask": "Edge",
    "Method": "EdgeRegressor",
    "Retained": false,
    "SingularValue": 82.9950218498,
    "VarianceExplained": 0.0033026825
  },
  "dropped_112": {
    "CumulativeVarianceExplained": 0.8561885529,
    "Mask": "Edge",
    "Method": "EdgeRegressor",
    "Retained": false,
    "SingularValue": 82.8880228726,
    "VarianceExplained": 0.0032941722
  },
  "dropped_113": {
    "CumulativeVarianceExplained": 0.8594690499,
    "Mask": "Edge",
    "Method": "EdgeRegressor",
    "Retained": false,
    "SingularValue": 82.715796102,
    "VarianceExplained": 0.003280497
  },
  "dropped_114": {
    "CumulativeVarianceExplained": 0.8627429183,
    "Mask": "Edge",
    "Method": "EdgeRegressor",
    "Retained": false,
    "SingularValue": 82.6321864536,
    "VarianceExplained": 0.0032738684
  },
  "dropped_115": {
    "CumulativeVarianceExplained": 0.8660036854,
    "Mask": "Edge",
    "Method": "EdgeRegressor",
    "Retained": false,
    "SingularValue": 82.4666822647,
    "VarianceExplained": 0.0032607671
  },
  "dropped_116": {
    "CumulativeVarianceExplained": 0.8692504411,
    "Mask": "Edge",
    "Method": "EdgeRegressor",
    "Retained": false,
    "SingularValue": 82.289313059,
    "VarianceExplained": 0.0032467557
  },
  "dropped_117": {
    "CumulativeVarianceExplained": 0.872490888,
    "Mask": "Edge",
    "Method": "EdgeRegressor",
    "Retained": false,
    "SingularValue": 82.2093260983,
    "VarianceExplained": 0.0032404469
  },
  "dropped_118": {
    "CumulativeVarianceExplained": 0.8757138195,
    "Mask": "Edge",
    "Method": "EdgeRegressor",
    "Retained": false,
    "SingularValue": 81.9868444323,
    "VarianceExplained": 0.0032229315
  },
  "dropped_119": {
    "CumulativeVarianceExplained": 0.8789182101,
    "Mask": "Edge",
    "Method": "EdgeRegressor",
    "Retained": false,
    "SingularValue": 81.7506758709,
    "VarianceExplained": 0.0032043905
  },
  "dropped_12": {
    "CumulativeVarianceExplained": 0.4565868213,
    "Mask": "Edge",
    "Method": "EdgeRegressor",
    "Retained": false,
    "SingularValue": 106.4144957834,
    "VarianceExplained": 0.005429556
  },
  "dropped_120": {
    "CumulativeVarianceExplained": 0.882111987,
    "Mask": "Edge",
    "Method": "EdgeRegressor",
    "Retained": false,
    "SingularValue": 81.6151760816,
    "VarianceExplained": 0.0031937769
  },
  "dropped_121": {
    "CumulativeVarianceExplained": 0.8852948234,
    "Mask": "Edge",
    "Method": "EdgeRegressor",
    "Retained": false,
    "SingularValue": 81.4752672883,
    "VarianceExplained": 0.0031828364
  },
  "dropped_122": {
    "CumulativeVarianceExplained": 0.8884673292,
    "Mask": "Edge",
    "Method": "EdgeRegressor",
    "Retained": false,
    "SingularValue": 81.3429355617,
    "VarianceExplained": 0.0031725057
  },
  "dropped_123": {
    "CumulativeVarianceExplained": 0.8916356518,
    "Mask": "Edge",
    "Method": "EdgeRegressor",
    "Retained": false,
    "SingularValue": 81.2892902498,
    "VarianceExplained": 0.0031683226
  },
  "dropped_124": {
    "CumulativeVarianceExplained": 0.8947905922,
    "Mask": "Edge",
    "Method": "EdgeRegressor",
    "Retained": false,
    "SingularValue": 81.1174360962,
    "VarianceExplained": 0.0031549404
  },
  "dropped_125": {
    "CumulativeVarianceExplained": 0.8979324019,
    "Mask": "Edge",
    "Method": "EdgeRegressor",
    "Retained": false,
    "SingularValue": 80.9484558881,
    "VarianceExplained": 0.0031418097
  },
  "dropped_126": {
    "CumulativeVarianceExplained": 0.901067797,
    "Mask": "Edge",
    "Method": "EdgeRegressor",
    "Retained": false,
    "SingularValue": 80.8657785115,
    "VarianceExplained": 0.0031353951
  },
  "dropped_127": {
    "CumulativeVarianceExplained": 0.9041856973,
    "Mask": "Edge",
    "Method": "EdgeRegressor",
    "Retained": false,
    "SingularValue": 80.6398551302,
    "VarianceExplained": 0.0031179002
  },
  "dropped_128": {
    "CumulativeVarianceExplained": 0.9072943755,
    "Mask": "Edge",
    "Method": "EdgeRegressor",
    "Retained": false,
    "SingularValue": 80.5205110535,
    "VarianceExplained": 0.0031086783
  },
  "dropped_129": {
    "CumulativeVarianceExplained": 0.9103976394,
    "Mask": "Edge",
    "Method": "EdgeRegressor",
    "Retained": false,
    "SingularValue": 80.4503582069,
    "VarianceExplained": 0.0031032638
  },
  "dropped_13": {
    "CumulativeVarianceExplained": 0.4619002187,
    "Mask": "Edge",
    "Method": "EdgeRegressor",
    "Retained": false,
    "SingularValue": 105.2700387651,
    "VarianceExplained": 0.0053133974
  },
  "dropped_130": {
    "CumulativeVarianceExplained": 0.9134931831,
    "Mask": "Edge",
    "Method": "EdgeRegressor",
    "Retained": false,
    "SingularValue": 80.3502265775,
    "VarianceExplained": 0.0030955437
  },
  "dropped_131": {
    "CumulativeVarianceExplained": 0.9165692486,
    "Mask": "Edge",
    "Method": "EdgeRegressor",
    "Retained": false,
    "SingularValue": 80.0970316982,
    "VarianceExplained": 0.0030760655
  },
  "dropped_132": {
    "CumulativeVarianceExplained": 0.9196212055,
    "Mask": "Edge",
    "Method": "EdgeRegressor",
    "Retained": false,
    "SingularValue": 79.7825346908,
    "VarianceExplained": 0.0030519569
  },
  "dropped_133": {
    "CumulativeVarianceExplained": 0.9226635653,
    "Mask": "Edge",
    "Method": "EdgeRegressor",
    "Retained": false,
    "SingularValue": 79.6569955686,
    "VarianceExplained": 0.0030423598
  },
  "dropped_134": {
    "CumulativeVarianceExplained": 0.9257008091,
    "Mask": "Edge",
    "Method": "EdgeRegressor",
    "Retained": false,
    "SingularValue": 79.5899907984,
    "VarianceExplained": 0.0030372437
  },
  "dropped_135": {
    "CumulativeVarianceExplained": 0.928727442,
    "Mask": "Edge",
    "Method": "EdgeRegressor",
    "Retained": false,
    "SingularValue": 79.4508429104,
    "VarianceExplained": 0.0030266329
  },
  "dropped_136": {
    "CumulativeVarianceExplained": 0.9317345359,
    "Mask": "Edge",
    "Method": "EdgeRegressor",
    "Retained": false,
    "SingularValue": 79.1939726401,
    "VarianceExplained": 0.0030070939
  },
  "dropped_137": {
    "CumulativeVarianceExplained": 0.9347361865,
    "Mask": "Edge",
    "Method": "EdgeRegressor",
    "Retained": false,
    "SingularValue": 79.1222634136,
    "VarianceExplained": 0.0030016506
  },
  "dropped_138": {
    "CumulativeVarianceExplained": 0.9377294154,
    "Mask": "Edge",
    "Method": "EdgeRegressor",
    "Retained": false,
    "SingularValue": 79.0111878428,
    "VarianceExplained": 0.0029932288
  },
  "dropped_139": {
    "CumulativeVarianceExplained": 0.9407150318,
    "Mask": "Edge",
    "Method": "EdgeRegressor",
    "Retained": false,
    "SingularValue": 78.9106534837,
    "VarianceExplained": 0.0029856164
  },
  "dropped_14": {
    "CumulativeVarianceExplained": 0.4671475775,
    "Mask": "Edge",
    "Method": "EdgeRegressor",
    "Retained": false,
    "SingularValue": 104.6138089821,
    "VarianceExplained": 0.0052473588
  },
  "dropped_140": {
    "CumulativeVarianceExplained": 0.9436953774,
    "Mask": "Edge",
    "Method": "EdgeRegressor",
    "Retained": false,
    "SingularValue": 78.8409672178,
    "VarianceExplained": 0.0029803456
  },
  "dropped_141": {
    "CumulativeVarianceExplained": 0.9466617825,
    "Mask": "Edge",
    "Method": "EdgeRegressor",
    "Retained": false,
    "SingularValue": 78.6563636966,
    "VarianceExplained": 0.0029664051
  },
  "dropped_142": {
    "CumulativeVarianceExplained": 0.9496149533,
    "Mask": "Edge",
    "Method": "EdgeRegressor",
    "Retained": false,
    "SingularValue": 78.4807087782,
    "VarianceExplained": 0.0029531708
  },
  "dropped_143": {
    "CumulativeVarianceExplained": 0.9525571489,
    "Mask": "Edge",
    "Method": "EdgeRegressor",
    "Retained": false,
    "SingularValue": 78.3347385945,
    "VarianceExplained": 0.0029421955
  },
  "dropped_144": {
    "CumulativeVarianceExplained": 0.95548214,
    "Mask": "Edge",
    "Method": "EdgeRegressor",
    "Retained": false,
    "SingularValue": 78.1053727746,
    "VarianceExplained": 0.0029249911
  },
  "dropped_145": {
    "CumulativeVarianceExplained": 0.9583993774,
    "Mask": "Edge",
    "Method": "EdgeRegressor",
    "Retained": false,
    "SingularValue": 78.0017809682,
    "VarianceExplained": 0.0029172374
  },
  "dropped_146": {
    "CumulativeVarianceExplained": 0.9613015152,
    "Mask": "Edge",
    "Method": "EdgeRegressor",
    "Retained": false,
    "SingularValue": 77.7996513289,
    "VarianceExplained": 0.0029021378
  },
  "dropped_147": {
    "CumulativeVarianceExplained": 0.9641895086,
    "Mask": "Edge",
    "Method": "EdgeRegressor",
    "Retained": false,
    "SingularValue": 77.6098297914,
    "VarianceExplained": 0.0028879934
  },
  "dropped_148": {
    "CumulativeVarianceExplained": 0.967069682,
    "Mask": "Edge",
    "Method": "EdgeRegressor",
    "Retained": false,
    "SingularValue": 77.5046831857,
    "VarianceExplained": 0.0028801733
  },
  "dropped_149": {
    "CumulativeVarianceExplained": 0.9699335091,
    "Mask": "Edge",
    "Method": "EdgeRegressor",
    "Retained": false,
    "SingularValue": 77.2844348362,
    "VarianceExplained": 0.0028638272
  },
  "dropped_15": {
    "CumulativeVarianceExplained": 0.4722874248,
    "Mask": "Edge",
    "Method": "EdgeRegressor",
    "Retained": false,
    "SingularValue": 103.536561767,
    "VarianceExplained": 0.0051398473
  },
  "dropped_150": {
    "CumulativeVarianceExplained": 0.9727859758,
    "Mask": "Edge",
    "Method": "EdgeRegressor",
    "Retained": false,
    "SingularValue": 77.1309926424,
    "VarianceExplained": 0.0028524667
  },
  "dropped_151": {
    "CumulativeVarianceExplained": 0.9756164551,
    "Mask": "Edge",
    "Method": "EdgeRegressor",
    "Retained": false,
    "SingularValue": 76.833147417,
    "VarianceExplained": 0.0028304793
  },
  "dropped_152": {
    "CumulativeVarianceExplained": 0.9784379575,
    "Mask": "Edge",
    "Method": "EdgeRegressor",
    "Retained": false,
    "SingularValue": 76.7112124204,
    "VarianceExplained": 0.0028215024
  },
  "dropped_153": {
    "CumulativeVarianceExplained": 0.9812366869,
    "Mask": "Edge",
    "Method": "EdgeRegressor",
    "Retained": false,
    "SingularValue": 76.4010078236,
    "VarianceExplained": 0.0027987294
  },
  "dropped_154": {
    "CumulativeVarianceExplained": 0.9840238826,
    "Mask": "Edge",
    "Method": "EdgeRegressor",
    "Retained": false,
    "SingularValue": 76.2434186277,
    "VarianceExplained": 0.0027871957
  },
  "dropped_155": {
    "CumulativeVarianceExplained": 0.9867921101,
    "Mask": "Edge",
    "Method": "EdgeRegressor",
    "Retained": false,
    "SingularValue": 75.9835407749,
    "VarianceExplained": 0.0027682276
  },
  "dropped_156": {
    "CumulativeVarianceExplained": 0.9895351074,
    "Mask": "Edge",
    "Method": "EdgeRegressor",
    "Retained": false,
    "SingularValue": 75.6364812517,
    "VarianceExplained": 0.0027429972
  },
  "dropped_157": {
    "CumulativeVarianceExplained": 0.9922717347,
    "Mask": "Edge",
    "Method": "EdgeRegressor",
    "Retained": false,
    "SingularValue": 75.5486074945,
    "VarianceExplained": 0.0027366273
  },
  "dropped_158": {
    "CumulativeVarianceExplained": 0.9949683216,
    "Mask": "Edge",
    "Method": "EdgeRegressor",
    "Retained": false,
    "SingularValue": 74.9938827865,
    "VarianceExplained": 0.0026965869
  },
  "dropped_159": {
    "CumulativeVarianceExplained": 0.9976147475,
    "Mask": "Edge",
    "Method": "EdgeRegressor",
    "Retained": false,
    "SingularValue": 74.2931037115,
    "VarianceExplained": 0.0026464259
  },
  "dropped_16": {
    "CumulativeVarianceExplained": 0.4773828627,
    "Mask": "Edge",
    "Method": "EdgeRegressor",
    "Retained": false,
    "SingularValue": 103.0883027055,
    "VarianceExplained": 0.0050954379
  },
  "dropped_160": {
    "CumulativeVarianceExplained": 1.0,
    "Mask": "Edge",
    "Method": "EdgeRegressor",
    "Retained": false,
    "SingularValue": 70.5319374845,
    "VarianceExplained": 0.0023852525
  },
  "dropped_161": {
    "CumulativeVarianceExplained": 1.0,
    "Mask": "Edge",
    "Method": "EdgeRegressor",
    "Retained": false,
    "SingularValue": 0.0,
    "VarianceExplained": 0.0
  },
  "dropped_162": {
    "CumulativeVarianceExplained": 1.0,
    "Mask": "Edge",
    "Method": "EdgeRegressor",
    "Retained": false,
    "SingularValue": 0.0,
    "VarianceExplained": 0.0
  },
  "dropped_163": {
    "CumulativeVarianceExplained": 1.0,
    "Mask": "Edge",
    "Method": "EdgeRegressor",
    "Retained": false,
    "SingularValue": 0.0,
    "VarianceExplained": 0.0
  },
  "dropped_164": {
    "CumulativeVarianceExplained": 1.0,
    "Mask": "Edge",
    "Method": "EdgeRegressor",
    "Retained": false,
    "SingularValue": 0.0,
    "VarianceExplained": 0.0
  },
  "dropped_165": {
    "CumulativeVarianceExplained": 1.0,
    "Mask": "Edge",
    "Method": "EdgeRegressor",
    "Retained": false,
    "SingularValue": 0.0,
    "VarianceExplained": 0.0
  },
  "dropped_17": {
    "CumulativeVarianceExplained": 0.4824582513,
    "Mask": "Edge",
    "Method": "EdgeRegressor",
    "Retained": false,
    "SingularValue": 102.885289469,
    "VarianceExplained": 0.0050753886
  },
  "dropped_18": {
    "CumulativeVarianceExplained": 0.4874920002,
    "Mask": "Edge",
    "Method": "EdgeRegressor",
    "Retained": false,
    "SingularValue": 102.462372063,
    "VarianceExplained": 0.0050337489
  },
  "dropped_19": {
    "CumulativeVarianceExplained": 0.4924531923,
    "Mask": "Edge",
    "Method": "EdgeRegressor",
    "Retained": false,
    "SingularValue": 101.7212422927,
    "VarianceExplained": 0.0049611921
  },
  "dropped_2": {
    "CumulativeVarianceExplained": 0.3988162754,
    "Mask": "Edge",
    "Method": "EdgeRegressor",
    "Retained": false,
    "SingularValue": 115.1027888635,
    "VarianceExplained": 0.0063523501
  },
  "dropped_20": {
    "CumulativeVarianceExplained": 0.4973862856,
    "Mask": "Edge",
    "Method": "EdgeRegressor",
    "Retained": false,
    "SingularValue": 101.4327721407,
    "VarianceExplained": 0.0049330932
  },
  "dropped_21": {
    "CumulativeVarianceExplained": 0.5022658263,
    "Mask": "Edge",
    "Method": "EdgeRegressor",
    "Retained": false,
    "SingularValue": 100.8807047393,
    "VarianceExplained": 0.0048795408
  },
  "dropped_22": {
    "CumulativeVarianceExplained": 0.5070625474,
    "Mask": "Edge",
    "Method": "EdgeRegressor",
    "Retained": false,
    "SingularValue": 100.020924478,
    "VarianceExplained": 0.0047967211
  },
  "dropped_23": {
    "CumulativeVarianceExplained": 0.5118169192,
    "Mask": "Edge",
    "Method": "EdgeRegressor",
    "Retained": false,
    "SingularValue": 99.5784139955,
    "VarianceExplained": 0.0047543718
  },
  "dropped_24": {
    "CumulativeVarianceExplained": 0.5165444891,
    "Mask": "Edge",
    "Method": "EdgeRegressor",
    "Retained": false,
    "SingularValue": 99.2973391792,
    "VarianceExplained": 0.0047275699
  },
  "dropped_25": {
    "CumulativeVarianceExplained": 0.5212406021,
    "Mask": "Edge",
    "Method": "EdgeRegressor",
    "Retained": false,
    "SingularValue": 98.9664291651,
    "VarianceExplained": 0.004696113
  },
  "dropped_26": {
    "CumulativeVarianceExplained": 0.5258797409,
    "Mask": "Edge",
    "Method": "EdgeRegressor",
    "Retained": false,
    "SingularValue": 98.3642575709,
    "VarianceExplained": 0.0046391389
  },
  "dropped_27": {
    "CumulativeVarianceExplained": 0.5304921067,
    "Mask": "Edge",
    "Method": "EdgeRegressor",
    "Retained": false,
    "SingularValue": 98.080010832,
    "VarianceExplained": 0.0046123658
  },
  "dropped_28": {
    "CumulativeVarianceExplained": 0.5350698501,
    "Mask": "Edge",
    "Method": "EdgeRegressor",
    "Retained": false,
    "SingularValue": 97.7112011643,
    "VarianceExplained": 0.0045777433
  },
  "dropped_29": {
    "CumulativeVarianceExplained": 0.5396372868,
    "Mask": "Edge",
    "Method": "EdgeRegressor",
    "Retained": false,
    "SingularValue": 97.601142306,
    "VarianceExplained": 0.0045674367
  },
  "dropped_3": {
    "CumulativeVarianceExplained": 0.4050158563,
    "Mask": "Edge",
    "Method": "EdgeRegressor",
    "Retained": false,
    "SingularValue": 113.710298144,
    "VarianceExplained": 0.0061995809
  },
  "dropped_30": {
    "CumulativeVarianceExplained": 0.5441704765,
    "Mask": "Edge",
    "Method": "EdgeRegressor",
    "Retained": false,
    "SingularValue": 97.2345443154,
    "VarianceExplained": 0.0045331898
  },
  "dropped_31": {
    "CumulativeVarianceExplained": 0.5486944055,
    "Mask": "Edge",
    "Method": "EdgeRegressor",
    "Retained": false,
    "SingularValue": 97.135173678,
    "VarianceExplained": 0.004523929
  },
  "dropped_32": {
    "CumulativeVarianceExplained": 0.5531611884,
    "Mask": "Edge",
    "Method": "EdgeRegressor",
    "Retained": false,
    "SingularValue": 96.5197197348,
    "VarianceExplained": 0.0044667828
  },
  "dropped_33": {
    "CumulativeVarianceExplained": 0.5576259113,
    "Mask": "Edge",
    "Method": "EdgeRegressor",
    "Retained": false,
    "SingularValue": 96.4974616218,
    "VarianceExplained": 0.0044647229
  },
  "dropped_34": {
    "CumulativeVarianceExplained": 0.5620726773,
    "Mask": "Edge",
    "Method": "EdgeRegressor",
    "Retained": false,
    "SingularValue": 96.30321167,
    "VarianceExplained": 0.004446766
  },
  "dropped_35": {
    "CumulativeVarianceExplained": 0.5664994027,
    "Mask": "Edge",
    "Method": "EdgeRegressor",
    "Retained": false,
    "SingularValue": 96.0859581298,
    "VarianceExplained": 0.0044267254
  },
  "dropped_36": {
    "CumulativeVarianceExplained": 0.5708880698,
    "Mask": "Edge",
    "Method": "EdgeRegressor",
    "Retained": false,
    "SingularValue": 95.6720213058,
    "VarianceExplained": 0.0043886671
  },
  "dropped_37": {
    "CumulativeVarianceExplained": 0.575253392,
    "Mask": "Edge",
    "Method": "EdgeRegressor",
    "Retained": false,
    "SingularValue": 95.4172262339,
    "VarianceExplained": 0.0043653223
  },
  "dropped_38": {
    "CumulativeVarianceExplained": 0.5796024276,
    "Mask": "Edge",
    "Method": "EdgeRegressor",
    "Retained": false,
    "SingularValue": 95.2390632582,
    "VarianceExplained": 0.0043490356
  },
  "dropped_39": {
    "CumulativeVarianceExplained": 0.5839234431,
    "Mask": "Edge",
    "Method": "EdgeRegressor",
    "Retained": false,
    "SingularValue": 94.9317622025,
    "VarianceExplained": 0.0043210155
  },
  "dropped_4": {
    "CumulativeVarianceExplained": 0.4111096176,
    "Mask": "Edge",
    "Method": "EdgeRegressor",
    "Retained": false,
    "SingularValue": 112.7356706254,
    "VarianceExplained": 0.0060937613
  },
  "dropped_40": {
    "CumulativeVarianceExplained": 0.5882158816,
    "Mask": "Edge",
    "Method": "EdgeRegressor",
    "Retained": false,
    "SingularValue": 94.6173261535,
    "VarianceExplained": 0.0042924385
  },
  "dropped_41": {
    "CumulativeVarianceExplained": 0.5924883729,
    "Mask": "Edge",
    "Method": "EdgeRegressor",
    "Retained": false,
    "SingularValue": 94.3972248833,
    "VarianceExplained": 0.0042724913
  },
  "dropped_42": {
    "CumulativeVarianceExplained": 0.5967177137,
    "Mask": "Edge",
    "Method": "EdgeRegressor",
    "Retained": false,
    "SingularValue": 93.919327143,
    "VarianceExplained": 0.0042293408
  },
  "dropped_43": {
    "CumulativeVarianceExplained": 0.6009268859,
    "Mask": "Edge",
    "Method": "EdgeRegressor",
    "Retained": false,
    "SingularValue": 93.6951217569,
    "VarianceExplained": 0.0042091722
  },
  "dropped_44": {
    "CumulativeVarianceExplained": 0.605121446,
    "Mask": "Edge",
    "Method": "EdgeRegressor",
    "Retained": false,
    "SingularValue": 93.5323499557,
    "VarianceExplained": 0.0041945602
  },
  "dropped_45": {
    "CumulativeVarianceExplained": 0.6092908502,
    "Mask": "Edge",
    "Method": "EdgeRegressor",
    "Retained": false,
    "SingularValue": 93.2514580646,
    "VarianceExplained": 0.0041694042
  },
  "dropped_46": {
    "CumulativeVarianceExplained": 0.6134578605,
    "Mask": "Edge",
    "Method": "EdgeRegressor",
    "Retained": false,
    "SingularValue": 93.2246838118,
    "VarianceExplained": 0.0041670103
  },
  "dropped_47": {
    "CumulativeVarianceExplained": 0.6175771741,
    "Mask": "Edge",
    "Method": "EdgeRegressor",
    "Retained": false,
    "SingularValue": 92.6896112311,
    "VarianceExplained": 0.0041193136
  },
  "dropped_48": {
    "CumulativeVarianceExplained": 0.6216787891,
    "Mask": "Edge",
    "Method": "EdgeRegressor",
    "Retained": false,
    "SingularValue": 92.490277345,
    "VarianceExplained": 0.0041016151
  },
  "dropped_49": {
    "CumulativeVarianceExplained": 0.6257679872,
    "Mask": "Edge",
    "Method": "EdgeRegressor",
    "Retained": false,
    "SingularValue": 92.3501709905,
    "VarianceExplained": 0.004089198
  },
  "dropped_5": {
    "CumulativeVarianceExplained": 0.4171555892,
    "Mask": "Edge",
    "Method": "EdgeRegressor",
    "Retained": false,
    "SingularValue": 112.2927408086,
    "VarianceExplained": 0.0060459715
  },
  "dropped_50": {
    "CumulativeVarianceExplained": 0.6298414364,
    "Mask": "Edge",
    "Method": "EdgeRegressor",
    "Retained": false,
    "SingularValue": 92.172164053,
    "VarianceExplained": 0.0040734492
  },
  "dropped_51": {
    "CumulativeVarianceExplained": 0.6338951216,
    "Mask": "Edge",
    "Method": "EdgeRegressor",
    "Retained": false,
    "SingularValue": 91.9482870503,
    "VarianceExplained": 0.0040536852
  },
  "dropped_52": {
    "CumulativeVarianceExplained": 0.6379353476,
    "Mask": "Edge",
    "Method": "EdgeRegressor",
    "Retained": false,
    "SingularValue": 91.7955154198,
    "VarianceExplained": 0.004040226
  },
  "dropped_53": {
    "CumulativeVarianceExplained": 0.6419606812,
    "Mask": "Edge",
    "Method": "EdgeRegressor",
    "Retained": false,
    "SingularValue": 91.6261783863,
    "VarianceExplained": 0.0040253336
  },
  "dropped_54": {
    "CumulativeVarianceExplained": 0.6459770133,
    "Mask": "Edge",
    "Method": "EdgeRegressor",
    "Retained": false,
    "SingularValue": 91.5236724473,
    "VarianceExplained": 0.0040163321
  },
  "dropped_55": {
    "CumulativeVarianceExplained": 0.6499752009,
    "Mask": "Edge",
    "Method": "EdgeRegressor",
    "Retained": false,
    "SingularValue": 91.3167015121,
    "VarianceExplained": 0.0039981876
  },
  "dropped_56": {
    "CumulativeVarianceExplained": 0.6539500728,
    "Mask": "Edge",
    "Method": "EdgeRegressor",
    "Retained": false,
    "SingularValue": 91.0500531683,
    "VarianceExplained": 0.0039748719
  },
  "dropped_57": {
    "CumulativeVarianceExplained": 0.6579159058,
    "Mask": "Edge",
    "Method": "EdgeRegressor",
    "Retained": false,
    "SingularValue": 90.9464691052,
    "VarianceExplained": 0.003965833
  },
  "dropped_58": {
    "CumulativeVarianceExplained": 0.6618572462,
    "Mask": "Edge",
    "Method": "EdgeRegressor",
    "Retained": false,
    "SingularValue": 90.6651964749,
    "VarianceExplained": 0.0039413404
  },
  "dropped_59": {
    "CumulativeVarianceExplained": 0.6657835054,
    "Mask": "Edge",
    "Method": "EdgeRegressor",
    "Retained": false,
    "SingularValue": 90.4915685269,
    "VarianceExplained": 0.0039262592
  },
  "dropped_6": {
    "CumulativeVarianceExplained": 0.4230191837,
    "Mask": "Edge",
    "Method": "EdgeRegressor",
    "Retained": false,
    "SingularValue": 110.5861140063,
    "VarianceExplained": 0.0058635945
  },
  "dropped_60": {
    "CumulativeVarianceExplained": 0.6696895012,
    "Mask": "Edge",
    "Method": "EdgeRegressor",
    "Retained": false,
    "SingularValue": 90.2577525007,
    "VarianceExplained": 0.0039059957
  },
  "dropped_61": {
    "CumulativeVarianceExplained": 0.6735860218,
    "Mask": "Edge",
    "Method": "EdgeRegressor",
    "Retained": false,
    "SingularValue": 90.1482127872,
    "VarianceExplained": 0.0038965206
  },
  "dropped_62": {
    "CumulativeVarianceExplained": 0.6774666106,
    "Mask": "Edge",
    "Method": "EdgeRegressor",
    "Retained": false,
    "SingularValue": 89.9637289138,
    "VarianceExplained": 0.0038805888
  },
  "dropped_63": {
    "CumulativeVarianceExplained": 0.6813453978,
    "Mask": "Edge",
    "Method": "EdgeRegressor",
    "Retained": false,
    "SingularValue": 89.9428426074,
    "VarianceExplained": 0.0038787872
  },
  "dropped_64": {
    "CumulativeVarianceExplained": 0.6852053513,
    "Mask": "Edge",
    "Method": "EdgeRegressor",
    "Retained": false,
    "SingularValue": 89.7242152314,
    "VarianceExplained": 0.0038599535
  },
  "dropped_65": {
    "CumulativeVarianceExplained": 0.6890515779,
    "Mask": "Edge",
    "Method": "EdgeRegressor",
    "Retained": false,
    "SingularValue": 89.5645324595,
    "VarianceExplained": 0.0038462265
  },
  "dropped_66": {
    "CumulativeVarianceExplained": 0.6928935007,
    "Mask": "Edge",
    "Method": "EdgeRegressor",
    "Retained": false,
    "SingularValue": 89.5144096375,
    "VarianceExplained": 0.0038419228
  },
  "dropped_67": {
    "CumulativeVarianceExplained": 0.6967094428,
    "Mask": "Edge",
    "Method": "EdgeRegressor",
    "Retained": false,
    "SingularValue": 89.2112284762,
    "VarianceExplained": 0.0038159421
  },
  "dropped_68": {
    "CumulativeVarianceExplained": 0.7005180675,
    "Mask": "Edge",
    "Method": "EdgeRegressor",
    "Retained": false,
    "SingularValue": 89.1256520763,
    "VarianceExplained": 0.0038086247
  },
  "dropped_69": {
    "CumulativeVarianceExplained": 0.7043197396,
    "Mask": "Edge",
    "Method": "EdgeRegressor",
    "Retained": false,
    "SingularValue": 89.0442668553,
    "VarianceExplained": 0.0038016721
  },
  "dropped_7": {
    "CumulativeVarianceExplained": 0.42881701,
    "Mask": "Edge",
    "Method": "EdgeRegressor",
    "Retained": false,
    "SingularValue": 109.9641777356,
    "VarianceExplained": 0.0057978263
  },
  "dropped_70": {
    "CumulativeVarianceExplained": 0.7080995244,
    "Mask": "Edge",
    "Method": "EdgeRegressor",
    "Retained": false,
    "SingularValue": 88.7875704558,
    "VarianceExplained": 0.0037797848
  },
  "dropped_71": {
    "CumulativeVarianceExplained": 0.7118670816,
    "Mask": "Edge",
    "Method": "EdgeRegressor",
    "Retained": false,
    "SingularValue": 88.6438391621,
    "VarianceExplained": 0.0037675572
  },
  "dropped_72": {
    "CumulativeVarianceExplained": 0.7156208848,
    "Mask": "Edge",
    "Method": "EdgeRegressor",
    "Retained": false,
    "SingularValue": 88.4818888779,
    "VarianceExplained": 0.0037538032
  },
  "dropped_73": {
    "CumulativeVarianceExplained": 0.7193632501,
    "Mask": "Edge",
    "Method": "EdgeRegressor",
    "Retained": false,
    "SingularValue": 88.3469819445,
    "VarianceExplained": 0.0037423652
  },
  "dropped_74": {
    "CumulativeVarianceExplained": 0.7231038065,
    "Mask": "Edge",
    "Method": "EdgeRegressor",
    "Retained": false,
    "SingularValue": 88.3256287334,
    "VarianceExplained": 0.0037405564
  },
  "dropped_75": {
    "CumulativeVarianceExplained": 0.7268296334,
    "Mask": "Edge",
    "Method": "EdgeRegressor",
    "Retained": false,
    "SingularValue": 88.1515529108,
    "VarianceExplained": 0.0037258269
  },
  "dropped_76": {
    "CumulativeVarianceExplained": 0.7305420473,
    "Mask": "Edge",
    "Method": "EdgeRegressor",
    "Retained": false,
    "SingularValue": 87.9927378749,
    "VarianceExplained": 0.003712414
  },
  "dropped_77": {
    "CumulativeVarianceExplained": 0.7342474403,
    "Mask": "Edge",
    "Method": "EdgeRegressor",
    "Retained": false,
    "SingularValue": 87.9094922342,
    "VarianceExplained": 0.003705393
  },
  "dropped_78": {
    "CumulativeVarianceExplained": 0.7379399234,
    "Mask": "Edge",
    "Method": "EdgeRegressor",
    "Retained": false,
    "SingularValue": 87.7562156808,
    "VarianceExplained": 0.003692483
  },
  "dropped_79": {
    "CumulativeVarianceExplained": 0.741627071,
    "Mask": "Edge",
    "Method": "EdgeRegressor",
    "Retained": false,
    "SingularValue": 87.6927918611,
    "VarianceExplained": 0.0036871476
  },
  "dropped_8": {
    "CumulativeVarianceExplained": 0.4345958887,
    "Mask": "Edge",
    "Method": "EdgeRegressor",
    "Retained": false,
    "SingularValue": 109.7843472602,
    "VarianceExplained": 0.0057788788
  },
  "dropped_80": {
    "CumulativeVarianceExplained": 0.7452991939,
    "Mask": "Edge",
    "Method": "EdgeRegressor",
    "Retained": false,
    "SingularValue": 87.5139399412,
    "VarianceExplained": 0.0036721229
  },
  "dropped_81": {
    "CumulativeVarianceExplained": 0.7489537095,
    "Mask": "Edge",
    "Method": "EdgeRegressor",
    "Retained": false,
    "SingularValue": 87.3038797573,
    "VarianceExplained": 0.0036545156
  },
  "dropped_82": {
    "CumulativeVarianceExplained": 0.752591015,
    "Mask": "Edge",
    "Method": "EdgeRegressor",
    "Retained": false,
    "SingularValue": 87.0980675641,
    "VarianceExplained": 0.0036373055
  },
  "dropped_83": {
    "CumulativeVarianceExplained": 0.7562243976,
    "Mask": "Edge",
    "Method": "EdgeRegressor",
    "Retained": false,
    "SingularValue": 87.0510877364,
    "VarianceExplained": 0.0036333827
  },
  "dropped_84": {
    "CumulativeVarianceExplained": 0.7598428708,
    "Mask": "Edge",
    "Method": "EdgeRegressor",
    "Retained": false,
    "SingularValue": 86.8722974801,
    "VarianceExplained": 0.0036184731
  },
  "dropped_85": {
    "CumulativeVarianceExplained": 0.7634516048,
    "Mask": "Edge",
    "Method": "EdgeRegressor",
    "Retained": false,
    "SingularValue": 86.7553106896,
    "VarianceExplained": 0.003608734
  },
  "dropped_86": {
    "CumulativeVarianceExplained": 0.7670232178,
    "Mask": "Edge",
    "Method": "EdgeRegressor",
    "Retained": false,
    "SingularValue": 86.3079564152,
    "VarianceExplained": 0.0035716131
  },
  "dropped_87": {
    "CumulativeVarianceExplained": 0.7705919227,
    "Mask": "Edge",
    "Method": "EdgeRegressor",
    "Retained": false,
    "SingularValue": 86.2728116451,
    "VarianceExplained": 0.0035687049
  },
  "dropped_88": {
    "CumulativeVarianceExplained": 0.7741472757,
    "Mask": "Edge",
    "Method": "EdgeRegressor",
    "Retained": false,
    "SingularValue": 86.1112702928,
    "VarianceExplained": 0.003555353
  },
  "dropped_89": {
    "CumulativeVarianceExplained": 0.7776893365,
    "Mask": "Edge",
    "Method": "EdgeRegressor",
    "Retained": false,
    "SingularValue": 85.9501491943,
    "VarianceExplained": 0.0035420607
  },
  "dropped_9": {
    "CumulativeVarianceExplained": 0.440209664,
    "Mask": "Edge",
    "Method": "EdgeRegressor",
    "Retained": false,
    "SingularValue": 108.204704996,
    "VarianceExplained": 0.0056137753
  },
  "dropped_90": {
    "CumulativeVarianceExplained": 0.7812117997,
    "Mask": "Edge",
    "Method": "EdgeRegressor",
    "Retained": false,
    "SingularValue": 85.7120466332,
    "VarianceExplained": 0.0035224632
  },
  "dropped_91": {
    "CumulativeVarianceExplained": 0.7847274658,
    "Mask": "Edge",
    "Method": "EdgeRegressor",
    "Retained": false,
    "SingularValue": 85.6293097791,
    "VarianceExplained": 0.0035156661
  },
  "dropped_92": {
    "CumulativeVarianceExplained": 0.7882371568,
    "Mask": "Edge",
    "Method": "EdgeRegressor",
    "Retained": false,
    "SingularValue": 85.5565123347,
    "VarianceExplained": 0.003509691
  },
  "dropped_93": {
    "CumulativeVarianceExplained": 0.7917332426,
    "Mask": "Edge",
    "Method": "EdgeRegressor",
    "Retained": false,
    "SingularValue": 85.390523602,
    "VarianceExplained": 0.0034960858
  },
  "dropped_94": {
    "CumulativeVarianceExplained": 0.7952229055,
    "Mask": "Edge",
    "Method": "EdgeRegressor",
    "Retained": false,
    "SingularValue": 85.3120481459,
    "VarianceExplained": 0.0034896629
  },
  "dropped_95": {
    "CumulativeVarianceExplained": 0.7987060093,
    "Mask": "Edge",
    "Method": "EdgeRegressor",
    "Retained": false,
    "SingularValue": 85.2318361363,
    "VarianceExplained": 0.0034831039
  },
  "dropped_96": {
    "CumulativeVarianceExplained": 0.8021787618,
    "Mask": "Edge",
    "Method": "EdgeRegressor",
    "Retained": false,
    "SingularValue": 85.1050925013,
    "VarianceExplained": 0.0034727525
  },
  "dropped_97": {
    "CumulativeVarianceExplained": 0.8056424736,
    "Mask": "Edge",
    "Method": "EdgeRegressor",
    "Retained": false,
    "SingularValue": 84.9942425896,
    "VarianceExplained": 0.0034637118
  },
  "dropped_98": {
    "CumulativeVarianceExplained": 0.809092938,
    "Mask": "Edge",
    "Method": "EdgeRegressor",
    "Retained": false,
    "SingularValue": 84.8315500572,
    "VarianceExplained": 0.0034504643
  },
  "dropped_99": {
    "CumulativeVarianceExplained": 0.8125310801,
    "Mask": "Edge",
    "Method": "EdgeRegressor",
    "Retained": false,
    "SingularValue": 84.6799407718,
    "VarianceExplained": 0.0034381421
  },
  "edge_comp_00": {
    "CumulativeVarianceExplained": 0.0424429273,
    "Mask": "Edge",
    "Method": "EdgeRegressor",
    "Retained": true,
    "SingularValue": 297.5235159915,
    "VarianceExplained": 0.0424429273
  },
  "edge_comp_01": {
    "CumulativeVarianceExplained": 0.0796262086,
    "Mask": "Edge",
    "Method": "EdgeRegressor",
    "Retained": true,
    "SingularValue": 278.4790240485,
    "VarianceExplained": 0.0371832812
  },
  "edge_comp_02": {
    "CumulativeVarianceExplained": 0.1079764418,
    "Mask": "Edge",
    "Method": "EdgeRegressor",
    "Retained": true,
    "SingularValue": 243.1626963822,
    "VarianceExplained": 0.0283502332
  },
  "edge_comp_03": {
    "CumulativeVarianceExplained": 0.132089447,
    "Mask": "Edge",
    "Method": "EdgeRegressor",
    "Retained": true,
    "SingularValue": 224.2561194849,
    "VarianceExplained": 0.0241130052
  },
  "edge_comp_04": {
    "CumulativeVarianceExplained": 0.1550532714,
    "Mask": "Edge",
    "Method": "EdgeRegressor",
    "Retained": true,
    "SingularValue": 218.8470720366,
    "VarianceExplained": 0.0229638243
  },
  "edge_comp_05": {
    "CumulativeVarianceExplained": 0.1775249456,
    "Mask": "Edge",
    "Method": "EdgeRegressor",
    "Retained": true,
    "SingularValue": 216.4892558236,
    "VarianceExplained": 0.0224716742
  },
  "edge_comp_06": {
    "CumulativeVarianceExplained": 0.1988957909,
    "Mask": "Edge",
    "Method": "EdgeRegressor",
    "Retained": true,
    "SingularValue": 211.1200513767,
    "VarianceExplained": 0.0213708453
  },
  "edge_comp_07": {
    "CumulativeVarianceExplained": 0.219543123,
    "Mask": "Edge",
    "Method": "EdgeRegressor",
    "Retained": true,
    "SingularValue": 207.515529981,
    "VarianceExplained": 0.0206473321
  },
  "edge_comp_08": {
    "CumulativeVarianceExplained": 0.2392497019,
    "Mask": "Edge",
    "Method": "EdgeRegressor",
    "Retained": true,
    "SingularValue": 202.732908726,
    "VarianceExplained": 0.019706579
  },
  "edge_comp_09": {
    "CumulativeVarianceExplained": 0.2521257134,
    "Mask": "Edge",
    "Method": "EdgeRegressor",
    "Retained": true,
    "SingularValue": 163.8737188477,
    "VarianceExplained": 0.0128760114
  },
  "edge_comp_10": {
    "CumulativeVarianceExplained": 0.2646867791,
    "Mask": "Edge",
    "Method": "EdgeRegressor",
    "Retained": true,
    "SingularValue": 161.8571454023,
    "VarianceExplained": 0.0125610657
  },
  "edge_comp_11": {
    "CumulativeVarianceExplained": 0.2760699878,
    "Mask": "Edge",
    "Method": "EdgeRegressor",
    "Retained": true,
    "SingularValue": 154.081671753,
    "VarianceExplained": 0.0113832087
  },
  "edge_comp_12": {
    "CumulativeVarianceExplained": 0.2866376893,
    "Mask": "Edge",
    "Method": "EdgeRegressor",
    "Retained": true,
    "SingularValue": 148.4598103192,
    "VarianceExplained": 0.0105677015
  },
  "edge_comp_13": {
    "CumulativeVarianceExplained": 0.2968027335,
    "Mask": "Edge",
    "Method": "EdgeRegressor",
    "Retained": true,
    "SingularValue": 145.6039871488,
    "VarianceExplained": 0.0101650442
  },
  "edge_comp_14": {
    "CumulativeVarianceExplained": 0.3061963061,
    "Mask": "Edge",
    "Method": "EdgeRegressor",
    "Retained": true,
    "SingularValue": 139.9696995875,
    "VarianceExplained": 0.0093935726
  },
  "edge_comp_15": {
    "CumulativeVarianceExplained": 0.3155042345,
    "Mask": "Edge",
    "Method": "EdgeRegressor",
    "Retained": true,
    "SingularValue": 139.330164882,
    "VarianceExplained": 0.0093079285
  },
  "edge_comp_16": {
    "CumulativeVarianceExplained": 0.3245463376,
    "Mask": "Edge",
    "Method": "EdgeRegressor",
    "Retained": true,
    "SingularValue": 137.3261863276,
    "VarianceExplained": 0.0090421031
  },
  "edge_comp_17": {
    "CumulativeVarianceExplained": 0.3332328575,
    "Mask": "Edge",
    "Method": "EdgeRegressor",
    "Retained": true,
    "SingularValue": 134.5989097691,
    "VarianceExplained": 0.0086865199
  },
  "edge_comp_18": {
    "CumulativeVarianceExplained": 0.3416428549,
    "Mask": "Edge",
    "Method": "EdgeRegressor",
    "Retained": true,
    "SingularValue": 132.4392041469,
    "VarianceExplained": 0.0084099974
  },
  "edge_comp_19": {
    "CumulativeVarianceExplained": 0.3498506036,
    "Mask": "Edge",
    "Method": "EdgeRegressor",
    "Retained": true,
    "SingularValue": 130.8370245345,
    "VarianceExplained": 0.0082077487
  },
  "edge_comp_20": {
    "CumulativeVarianceExplained": 0.3576045869,
    "Mask": "Edge",
    "Method": "EdgeRegressor",
    "Retained": true,
    "SingularValue": 127.1689437974,
    "VarianceExplained": 0.0077539833
  },
  "edge_comp_21": {
    "CumulativeVarianceExplained": 0.365171207,
    "Mask": "Edge",
    "Method": "EdgeRegressor",
    "Retained": true,
    "SingularValue": 125.6231259969,
    "VarianceExplained": 0.0075666201
  },
  "edge_comp_22": {
    "CumulativeVarianceExplained": 0.3722174148,
    "Mask": "Edge",
    "Method": "EdgeRegressor",
    "Retained": true,
    "SingularValue": 121.2261618125,
    "VarianceExplained": 0.0070462078
  },
  "edge_comp_23": {
    "CumulativeVarianceExplained": 0.3791049573,
    "Mask": "Edge",
    "Method": "EdgeRegressor",
    "Retained": true,
    "SingularValue": 119.8535160433,
    "VarianceExplained": 0.0068875425
  },
  "t_comp_cor_00": {
    "CumulativeVarianceExplained": 0.1739075107,
    "Method": "tCompCor",
    "Retained": true,
    "SingularValue": 154.2418473237,
    "VarianceExplained": 0.1739075107
  },
  "t_comp_cor_01": {
    "CumulativeVarianceExplained": 0.3143287341,
    "Method": "tCompCor",
    "Retained": true,
    "SingularValue": 138.5987855779,
    "VarianceExplained": 0.1404212234
  },
  "t_comp_cor_02": {
    "CumulativeVarianceExplained": 0.4397082996,
    "Method": "tCompCor",
    "Retained": true,
    "SingularValue": 130.9653563188,
    "VarianceExplained": 0.1253795655
  },
  "t_comp_cor_03": {
    "CumulativeVarianceExplained": 0.4912361752,
    "Method": "tCompCor",
    "Retained": true,
    "SingularValue": 83.9584026592,
    "VarianceExplained": 0.0515278756
  },
  "t_comp_cor_04": {
    "CumulativeVarianceExplained": 0.5283500275,
    "Method": "tCompCor",
    "Retained": true,
    "SingularValue": 71.2542980783,
    "VarianceExplained": 0.0371138523
  },
  "w_comp_cor_00": {
    "CumulativeVarianceExplained": 0.0206845977,
    "Mask": "WM",
    "Method": "aCompCor",
    "Retained": true,
    "SingularValue": 68.1279448951,
    "VarianceExplained": 0.0206845977
  },
  "w_comp_cor_01": {
    "CumulativeVarianceExplained": 0.0393181576,
    "Mask": "WM",
    "Method": "aCompCor",
    "Retained": true,
    "SingularValue": 64.6620792899,
    "VarianceExplained": 0.0186335599
  },
  "w_comp_cor_02": {
    "CumulativeVarianceExplained": 0.0531444267,
    "Mask": "WM",
    "Method": "aCompCor",
    "Retained": true,
    "SingularValue": 55.6998791981,
    "VarianceExplained": 0.0138262692
  },
  "w_comp_cor_03": {
    "CumulativeVarianceExplained": 0.0656947195,
    "Mask": "WM",
    "Method": "aCompCor",
    "Retained": true,
    "SingularValue": 53.0675059169,
    "VarianceExplained": 0.0125502927
  },
  "w_comp_cor_04": {
    "CumulativeVarianceExplained": 0.0759184183,
    "Mask": "WM",
    "Method": "aCompCor",
    "Retained": true,
    "SingularValue": 47.8967200477,
    "VarianceExplained": 0.0102236989
  },
  "w_comp_cor_05": {
    "CumulativeVarianceExplained": 0.0859937868,
    "Mask": "WM",
    "Method": "aCompCor",
    "Retained": true,
    "SingularValue": 47.5479960276,
    "VarianceExplained": 0.0100753684
  },
  "w_comp_cor_06": {
    "CumulativeVarianceExplained": 0.0959534255,
    "Mask": "WM",
    "Method": "aCompCor",
    "Retained": true,
    "SingularValue": 47.2741295164,
    "VarianceExplained": 0.0099596387
  },
  "w_comp_cor_07": {
    "CumulativeVarianceExplained": 0.1058246316,
    "Mask": "WM",
    "Method": "aCompCor",
    "Retained": true,
    "SingularValue": 47.0637859835,
    "VarianceExplained": 0.0098712062
  },
  "w_comp_cor_08": {
    "CumulativeVarianceExplained": 0.1154838534,
    "Mask": "WM",
    "Method": "aCompCor",
    "Retained": true,
    "SingularValue": 46.5556954387,
    "VarianceExplained": 0.0096592218
  },
  "w_comp_cor_09": {
    "CumulativeVarianceExplained": 0.1250493869,
    "Mask": "WM",
    "Method": "aCompCor",
    "Retained": true,
    "SingularValue": 46.3293650423,
    "VarianceExplained": 0.0095655335
  },
  "w_comp_cor_10": {
    "CumulativeVarianceExplained": 0.1345114653,
    "Mask": "WM",
    "Method": "aCompCor",
    "Retained": true,
    "SingularValue": 46.0781484493,
    "VarianceExplained": 0.0094620784
  },
  "w_comp_cor_11": {
    "CumulativeVarianceExplained": 0.1437500078,
    "Mask": "WM",
    "Method": "aCompCor",
    "Retained": true,
    "SingularValue": 45.5306111226,
    "VarianceExplained": 0.0092385425
  },
  "w_comp_cor_12": {
    "CumulativeVarianceExplained": 0.1529410769,
    "Mask": "WM",
    "Method": "aCompCor",
    "Retained": true,
    "SingularValue": 45.4134780428,
    "VarianceExplained": 0.0091910691
  },
  "w_comp_cor_13": {
    "CumulativeVarianceExplained": 0.162042775,
    "Mask": "WM",
    "Method": "aCompCor",
    "Retained": true,
    "SingularValue": 45.1921458707,
    "VarianceExplained": 0.0091016982
  },
  "w_comp_cor_14": {
    "CumulativeVarianceExplained": 0.1709967275,
    "Mask": "WM",
    "Method": "aCompCor",
    "Retained": true,
    "SingularValue": 44.8238486132,
    "VarianceExplained": 0.0089539525
  },
  "w_comp_cor_15": {
    "CumulativeVarianceExplained": 0.1798561725,
    "Mask": "WM",
    "Method": "aCompCor",
    "Retained": true,
    "SingularValue": 44.5866668636,
    "VarianceExplained": 0.008859445
  },
  "w_comp_cor_16": {
    "CumulativeVarianceExplained": 0.1886854571,
    "Mask": "WM",
    "Method": "aCompCor",
    "Retained": true,
    "SingularValue": 44.5107085433,
    "VarianceExplained": 0.0088292846
  },
  "w_comp_cor_17": {
    "CumulativeVarianceExplained": 0.1974089966,
    "Mask": "WM",
    "Method": "aCompCor",
    "Retained": true,
    "SingularValue": 44.2433613883,
    "VarianceExplained": 0.0087235395
  },
  "w_comp_cor_18": {
    "CumulativeVarianceExplained": 0.2060482197,
    "Mask": "WM",
    "Method": "aCompCor",
    "Retained": true,
    "SingularValue": 44.0290275822,
    "VarianceExplained": 0.0086392231
  },
  "w_comp_cor_19": {
    "CumulativeVarianceExplained": 0.2146150187,
    "Mask": "WM",
    "Method": "aCompCor",
    "Retained": true,
    "SingularValue": 43.84408769,
    "VarianceExplained": 0.008566799
  },
  "w_comp_cor_20": {
    "CumulativeVarianceExplained": 0.2231047197,
    "Mask": "WM",
    "Method": "aCompCor",
    "Retained": true,
    "SingularValue": 43.6463514967,
    "VarianceExplained": 0.008489701
  },
  "w_comp_cor_21": {
    "CumulativeVarianceExplained": 0.2314925229,
    "Mask": "WM",
    "Method": "aCompCor",
    "Retained": true,
    "SingularValue": 43.3836279897,
    "VarianceExplained": 0.0083878033
  },
  "w_comp_cor_22": {
    "CumulativeVarianceExplained": 0.2398012329,
    "Mask": "WM",
    "Method": "aCompCor",
    "Retained": true,
    "SingularValue": 43.1785991394,
    "VarianceExplained": 0.0083087099
  },
  "w_comp_cor_23": {
    "CumulativeVarianceExplained": 0.2480254036,
    "Mask": "WM",
    "Method": "aCompCor",
    "Retained": true,
    "SingularValue": 42.9583713929,
    "VarianceExplained": 0.0082241707
  },
  "w_comp_cor_24": {
    "CumulativeVarianceExplained": 0.2562298541,
    "Mask": "WM",
    "Method": "aCompCor",
    "Retained": true,
    "SingularValue": 42.9068368177,
    "VarianceExplained": 0.0082044505
  },
  "w_comp_cor_25": {
    "CumulativeVarianceExplained": 0.264332792,
    "Mask": "WM",
    "Method": "aCompCor",
    "Retained": true,
    "SingularValue": 42.640570174,
    "VarianceExplained": 0.0081029379
  },
  "w_comp_cor_26": {
    "CumulativeVarianceExplained": 0.2723139759,
    "Mask": "WM",
    "Method": "aCompCor",
    "Retained": true,
    "SingularValue": 42.31900116,
    "VarianceExplained": 0.0079811839
  },
  "w_comp_cor_27": {
    "CumulativeVarianceExplained": 0.2802527434,
    "Mask": "WM",
    "Method": "aCompCor",
    "Retained": true,
    "SingularValue": 42.20639799,
    "VarianceExplained": 0.0079387675
  },
  "w_comp_cor_28": {
    "CumulativeVarianceExplained": 0.2880597045,
    "Mask": "WM",
    "Method": "aCompCor",
    "Retained": true,
    "SingularValue": 41.8545578329,
    "VarianceExplained": 0.0078069611
  },
  "w_comp_cor_29": {
    "CumulativeVarianceExplained": 0.2958286275,
    "Mask": "WM",
    "Method": "aCompCor",
    "Retained": true,
    "SingularValue": 41.7524684626,
    "VarianceExplained": 0.007768923
  },
  "w_comp_cor_30": {
    "CumulativeVarianceExplained": 0.3035537677,
    "Mask": "WM",
    "Method": "aCompCor",
    "Retained": true,
    "SingularValue": 41.6346516119,
    "VarianceExplained": 0.0077251402
  },
  "w_comp_cor_31": {
    "CumulativeVarianceExplained": 0.3112539559,
    "Mask": "WM",
    "Method": "aCompCor",
    "Retained": true,
    "SingularValue": 41.5673578093,
    "VarianceExplained": 0.0077001882
  },
  "w_comp_cor_32": {
    "CumulativeVarianceExplained": 0.3189249291,
    "Mask": "WM",
    "Method": "aCompCor",
    "Retained": true,
    "SingularValue": 41.4884283426,
    "VarianceExplained": 0.0076709732
  },
  "w_comp_cor_33": {
    "CumulativeVarianceExplained": 0.3264658387,
    "Mask": "WM",
    "Method": "aCompCor",
    "Retained": true,
    "SingularValue": 41.1352001347,
    "VarianceExplained": 0.0075409095
  },
  "w_comp_cor_34": {
    "CumulativeVarianceExplained": 0.3339248758,
    "Mask": "WM",
    "Method": "aCompCor",
    "Retained": true,
    "SingularValue": 40.9112862252,
    "VarianceExplained": 0.0074590371
  },
  "w_comp_cor_35": {
    "CumulativeVarianceExplained": 0.3413481785,
    "Mask": "WM",
    "Method": "aCompCor",
    "Retained": true,
    "SingularValue": 40.8131705863,
    "VarianceExplained": 0.0074233027
  },
  "w_comp_cor_36": {
    "CumulativeVarianceExplained": 0.3487263651,
    "Mask": "WM",
    "Method": "aCompCor",
    "Retained": true,
    "SingularValue": 40.6889579027,
    "VarianceExplained": 0.0073781866
  },
  "w_comp_cor_37": {
    "CumulativeVarianceExplained": 0.3560427011,
    "Mask": "WM",
    "Method": "aCompCor",
    "Retained": true,
    "SingularValue": 40.5180531676,
    "VarianceExplained": 0.007316336
  },
  "w_comp_cor_38": {
    "CumulativeVarianceExplained": 0.363317862,
    "Mask": "WM",
    "Method": "aCompCor",
    "Retained": true,
    "SingularValue": 40.4038778954,
    "VarianceExplained": 0.0072751609
  },
  "w_comp_cor_39": {
    "CumulativeVarianceExplained": 0.3705394661,
    "Mask": "WM",
    "Method": "aCompCor",
    "Retained": true,
    "SingularValue": 40.2548848289,
    "VarianceExplained": 0.0072216041
  },
  "w_comp_cor_40": {
    "CumulativeVarianceExplained": 0.3776940046,
    "Mask": "WM",
    "Method": "aCompCor",
    "Retained": true,
    "SingularValue": 40.0675290128,
    "VarianceExplained": 0.0071545384
  },
  "w_comp_cor_41": {
    "CumulativeVarianceExplained": 0.3848153572,
    "Mask": "WM",
    "Method": "aCompCor",
    "Retained": true,
    "SingularValue": 39.9744958111,
    "VarianceExplained": 0.0071213526
  },
  "w_comp_cor_42": {
    "CumulativeVarianceExplained": 0.3918602036,
    "Mask": "WM",
    "Method": "aCompCor",
    "Retained": true,
    "SingularValue": 39.7591887744,
    "VarianceExplained": 0.0070448464
  },
  "w_comp_cor_43": {
    "CumulativeVarianceExplained": 0.3988394759,
    "Mask": "WM",
    "Method": "aCompCor",
    "Retained": true,
    "SingularValue": 39.573714801,
    "VarianceExplained": 0.0069792723
  },
  "w_comp_cor_44": {
    "CumulativeVarianceExplained": 0.4057753266,
    "Mask": "WM",
    "Method": "aCompCor",
    "Retained": true,
    "SingularValue": 39.4504186693,
    "VarianceExplained": 0.0069358507
  },
  "w_comp_cor_45": {
    "CumulativeVarianceExplained": 0.4125964398,
    "Mask": "WM",
    "Method": "aCompCor",
    "Retained": true,
    "SingularValue": 39.1227503705,
    "VarianceExplained": 0.0068211132
  },
  "w_comp_cor_46": {
    "CumulativeVarianceExplained": 0.4193795825,
    "Mask": "WM",
    "Method": "aCompCor",
    "Retained": true,
    "SingularValue": 39.0137076639,
    "VarianceExplained": 0.0067831427
  },
  "w_comp_cor_47": {
    "CumulativeVarianceExplained": 0.4261096142,
    "Mask": "WM",
    "Method": "aCompCor",
    "Retained": true,
    "SingularValue": 38.86067182,
    "VarianceExplained": 0.0067300317
  },
  "w_comp_cor_48": {
    "CumulativeVarianceExplained": 0.4328280888,
    "Mask": "WM",
    "Method": "aCompCor",
    "Retained": true,
    "SingularValue": 38.8272909135,
    "VarianceExplained": 0.0067184746
  },
  "w_comp_cor_49": {
    "CumulativeVarianceExplained": 0.43950786,
    "Mask": "WM",
    "Method": "aCompCor",
    "Retained": true,
    "SingularValue": 38.7152923962,
    "VarianceExplained": 0.0066797712
  },
  "w_comp_cor_50": {
    "CumulativeVarianceExplained": 0.4461380956,
    "Mask": "WM",
    "Method": "aCompCor",
    "Retained": true,
    "SingularValue": 38.5714733421,
    "VarianceExplained": 0.0066302356
  },
  "w_comp_cor_51": {
    "CumulativeVarianceExplained": 0.4527034901,
    "Mask": "WM",
    "Method": "aCompCor",
    "Retained": true,
    "SingularValue": 38.382403331,
    "VarianceExplained": 0.0065653946
  },
  "w_comp_cor_52": {
    "CumulativeVarianceExplained": 0.4592229368,
    "Mask": "WM",
    "Method": "aCompCor",
    "Retained": true,
    "SingularValue": 38.2478580159,
    "VarianceExplained": 0.0065194467
  },
  "w_comp_cor_53": {
    "CumulativeVarianceExplained": 0.4656886432,
    "Mask": "WM",
    "Method": "aCompCor",
    "Retained": true,
    "SingularValue": 38.0898916931,
    "VarianceExplained": 0.0064657064
  },
  "w_comp_cor_54": {
    "CumulativeVarianceExplained": 0.4721447373,
    "Mask": "WM",
    "Method": "aCompCor",
    "Retained": true,
    "SingularValue": 38.0615678623,
    "VarianceExplained": 0.0064560941
  },
  "w_comp_cor_55": {
    "CumulativeVarianceExplained": 0.4785436691,
    "Mask": "WM",
    "Method": "aCompCor",
    "Retained": true,
    "SingularValue": 37.8926946787,
    "VarianceExplained": 0.0063989318
  },
  "w_comp_cor_56": {
    "CumulativeVarianceExplained": 0.4848895055,
    "Mask": "WM",
    "Method": "aCompCor",
    "Retained": true,
    "SingularValue": 37.7351592168,
    "VarianceExplained": 0.0063458365
  },
  "w_comp_cor_57": {
    "CumulativeVarianceExplained": 0.4911880449,
    "Mask": "WM",
    "Method": "aCompCor",
    "Retained": true,
    "SingularValue": 37.5942715031,
    "VarianceExplained": 0.0062985394
  },
  "w_comp_cor_58": {
    "CumulativeVarianceExplained": 0.4974515917,
    "Mask": "WM",
    "Method": "aCompCor",
    "Retained": true,
    "SingularValue": 37.4896955476,
    "VarianceExplained": 0.0062635468
  },
  "w_comp_cor_59": {
    "CumulativeVarianceExplained": 0.5036904522,
    "Mask": "WM",
    "Method": "aCompCor",
    "Retained": true,
    "SingularValue": 37.4157441771,
    "VarianceExplained": 0.0062388605
  }
}